whooshpad/__init__.py
whooshpad/__main__.py
whooshpad/server.py
whooshpad-0.1.2.dist-info/METADATA
whooshpad-0.1.2.dist-info/WHEEL
whooshpad-0.1.2.dist-info/entry_points.txt
whooshpad-0.1.2.dist-info/licenses/LICENSE
whooshpad-0.1.2.dist-info/RECORD
