Metadata-Version: 2.4
Name: whooshpad
Version: 0.1.2
Summary: A mobile-friendly remote control for MyWhoosh virtual cycling
Project-URL: Homepage, https://github.com/scorphus/whooshpad
Project-URL: Repository, https://github.com/scorphus/whooshpad
Project-URL: Issues, https://github.com/scorphus/whooshpad/issues
Author-email: Pablo Santiago Blum de Aguiar <scorphus@gmail.com>
License-Expression: BSD-3-Clause
License-File: LICENSE
Keywords: cycling,mywhoosh,remote,shifter,virtual
Classifier: Development Status :: 4 - Beta
Classifier: Environment :: Console
Classifier: Intended Audience :: End Users/Desktop
Classifier: License :: OSI Approved :: BSD License
Classifier: Operating System :: OS Independent
Classifier: Programming Language :: Python :: 3
Classifier: Programming Language :: Python :: 3.10
Classifier: Programming Language :: Python :: 3.11
Classifier: Programming Language :: Python :: 3.12
Classifier: Programming Language :: Python :: 3.13
Classifier: Topic :: Games/Entertainment
Requires-Python: >=3.10
Requires-Dist: pynput>=1.7.0
